liron_utils/__init__.py
liron_utils/Clone Submodules/README.md
liron_utils/Export Module/README.md
liron_utils/MATLAB/README.md
liron_utils/MATLAB/utils/progressbar/CHANGELOG.md
liron_utils/MATLAB/utils/progressbar/README.md
liron_utils/New Python Environment/README.md
liron_utils/New Python Environment/requirements.txt
liron_utils/files/__init__.py
liron_utils/files/csv.py
liron_utils/files/docx.py
liron_utils/files/files.py
liron_utils/files/json.py
liron_utils/files/pdf.py
liron_utils/graphics/__init__.py
liron_utils/graphics/axes.py
liron_utils/graphics/base.py
liron_utils/graphics/plotting.py
liron_utils/graphics/_tests/_plotting.py
liron_utils/graphics/_tests/_tests.py
liron_utils/graphics/utils/COLORS.py
liron_utils/graphics/utils/__init__.py
liron_utils/graphics/utils/default_kwargs.py
liron_utils/graphics/utils/etc.py
liron_utils/graphics/utils/rc_params.py
liron_utils/machine_learning/__init__.py
liron_utils/machine_learning/machine_learning.py
liron_utils/manim_animations/__init__.py
liron_utils/manim_animations/base.py
liron_utils/manim_animations/tests/plot_complex_functions.py
liron_utils/manim_animations/tests/test__1.py
liron_utils/pure_python/__init__.py
liron_utils/pure_python/base.py
liron_utils/pure_python/decorators.py
liron_utils/pure_python/dicts.py
liron_utils/pure_python/docstring.py
liron_utils/pure_python/imports.py
liron_utils/pure_python/logs.py
liron_utils/pure_python/os.py
liron_utils/pure_python/parallel.py
liron_utils/pure_python/pip.py
liron_utils/pure_python/prints.py
liron_utils/pure_python/progress_bar.py
liron_utils/pure_python/_tests/_logs.py
liron_utils/pure_python/_tests/_parallel.py
liron_utils/signal_processing/__init__.py
liron_utils/signal_processing/base.py
liron_utils/signal_processing/filtering.py
liron_utils/signal_processing/fitting.py
liron_utils/signal_processing/signal.py
liron_utils/signal_processing/sp_audio.py
liron_utils/signal_processing/sp_image.py
liron_utils/signal_processing/stats.py
liron_utils-2025.11.16.dist-info/licenses/LICENSE
liron_utils-2025.11.16.dist-info/METADATA
liron_utils-2025.11.16.dist-info/WHEEL
liron_utils-2025.11.16.dist-info/top_level.txt
liron_utils-2025.11.16.dist-info/RECORD
