Metadata-Version: 2.4
Name: liron-utils
Version: 2025.11.16
Summary: Utilities module
Author-email: Liron Stettiner <lironst1@gmail.com>
License-Expression: MIT
Project-URL: Homepage, https://github.com/lironst1/liron-utils
Requires-Python: >=3.10
License-File: LICENSE
Requires-Dist: audioread
Requires-Dist: colorama
Requires-Dist: ipython
Requires-Dist: matplotlib
Requires-Dist: natsort
Requires-Dist: numpy
Requires-Dist: pandas
Requires-Dist: scikit-learn
Requires-Dist: scipy
Requires-Dist: soundfile
Requires-Dist: sympy
Requires-Dist: tqdm
Requires-Dist: uncertainties
Provides-Extra: extra
Requires-Dist: docx; extra == "extra"
Requires-Dist: manim; extra == "extra"
Requires-Dist: pytube; extra == "extra"
Requires-Dist: PyPDF2; extra == "extra"
Provides-Extra: dev
Requires-Dist: black; extra == "dev"
Requires-Dist: mypy; extra == "dev"
Requires-Dist: pylint; extra == "dev"
Requires-Dist: types-tqdm; extra == "dev"
Requires-Dist: tox<5.0.0,>=4.32.0; extra == "dev"
Provides-Extra: tests
Requires-Dist: pytest; extra == "tests"
Requires-Dist: pytest-cov; extra == "tests"
Requires-Dist: pytest-html; extra == "tests"
Requires-Dist: pytest-xdist[psutil]; extra == "tests"
Provides-Extra: all
Requires-Dist: liron-utils[extra]; extra == "all"
Requires-Dist: liron-utils[dev]; extra == "all"
Requires-Dist: liron-utils[tests]; extra == "all"
Dynamic: license-file
